<?xml version="1.0"?>
<catalog><product_item><id_product>1</id_product><info_item><name>PlayStation 4</name><price>250</price><stock>84</stock></info_item></product_item><product_item><id_product>2</id_product><info_item><name>PlayStation 5</name><price>500</price><stock>100</stock></info_item></product_item><product_item><id_product>3</id_product><info_item><name>Xbox Series S</name><price>400</price><stock>100</stock></info_item></product_item><product_item><id_product>4</id_product><info_item><name>Nintendo Switch</name><price>320</price><stock>100</stock></info_item></product_item><product_item><id_product>5</id_product><info_item><name>PS5</name><price>500</price><stock>50</stock></info_item></product_item></catalog>
